README.rst
setup.cfg
setup.py
gobench/__init__.py
gobench/bench.py
gobench/exec.py
gobench/pprof.py
gobench/util.py
gobench.egg-info/PKG-INFO
gobench.egg-info/SOURCES.txt
gobench.egg-info/dependency_links.txt
gobench.egg-info/top_level.txt