Metadata-Version: 1.1
Name: gobench
Version: 1.0.1
Summary: Python module for Go benchmark github.com/sudachen/benchmark
Home-page: https://github.com/sudachen/benchmark
Author: Alexey Sudachen
Author-email: alexey@sudachen.name
License: UNKNOWN
Keywords: golang testing development
Platform: UNKNOWN
Classifier: Development Status :: 4 - Beta
Classifier: Intended Audience :: Developers
Classifier: Topic :: Software Development :: Testing
Classifier: License :: OSI Approved :: Apache Software License
Classifier: Programming Language :: Python :: 3
Classifier: Programming Language :: Python :: 3.4
Classifier: Programming Language :: Python :: 3.5
Classifier: Programming Language :: Python :: 3.6
